pytcl/__init__.py
pytcl/call.py
pytcl/error.py
pytcl/execute.py
pytcl/execute.tcl
pytcl/pytcl.py
pytcl/value.py
pytcl/vivado.py
pytcl_eda-0.3.0.dist-info/METADATA
pytcl_eda-0.3.0.dist-info/WHEEL
pytcl_eda-0.3.0.dist-info/RECORD
